{"state":"cached","ttl":300000,"createdAt":1716815810795,"data":{"data":[{"breakup":"1980-06-10","freezeup":"1979-12-12","date":"1979-01-01T00:00:00.000Z","station":"abisko","position":[68.3538,18.8166]}],"status":200,"statusText":"OK","headers":{"date":"Mon, 27 May 2024 13:16:50 GMT","content-type":"application/json; charset=utf-8","content-length":"132","connection":"keep-alive","set-cookie":["INGRESSCOOKIE=1716815808.589.1640.273967|e1f8272610c1bd8c52dc26ca2c9db709; Path=/; Secure; HttpOnly","glimworks1.sid=s%3A5SI6nyg7LMet0wN7RWM38BQGSGkogekV.d%2BkgNfTTYGpMo10afUljIIGQTzINzm2CXrGLq6DCjd0; Domain=.glimworks.se; Path=/; Expires=Wed, 26 Jun 2024 13:16:50 GMT; HttpOnly"],"x-powered-by":"Express","etag":"W/\"84-dhCsO+wigg8DF0E7R27KaOpOaiw\"","vary":"Accept-Encoding","strict-transport-security":"max-age=15724800; includeSubDomains","x-axios-cache-stale-if-error":"300000"}}}