{"state":"cached","ttl":300000,"createdAt":1716810353740,"data":{"data":[{"nhem_temp":".19","date":"1993-01-01T00:00:00.000Z","station":"nhem","position":[22.98865,36.51698]},{"nhem_temp":".37","date":"1994-01-01T00:00:00.000Z","station":"nhem","position":[22.98865,36.51698]}],"status":200,"statusText":"OK","headers":{"date":"Mon, 27 May 2024 11:45:53 GMT","content-type":"application/json; charset=utf-8","content-length":"205","connection":"keep-alive","set-cookie":["INGRESSCOOKIE=1716810354.616.1736.144031|e1f8272610c1bd8c52dc26ca2c9db709; Path=/; Secure; HttpOnly","glimworks1.sid=s%3A6CU2GK5rtjBsXBsjE_-tU3JSbZB10orN.%2Fulb%2FDnC1PAvKeKs0w2%2Bb6NrCJ39ye48TZZiZO9UMeQ; Domain=.glimworks.se; Path=/; Expires=Wed, 26 Jun 2024 11:45:53 GMT; HttpOnly"],"x-powered-by":"Express","etag":"W/\"cd-KynMbAZPbbpK8++osNPadZsDaoM\"","vary":"Accept-Encoding","strict-transport-security":"max-age=15724800; includeSubDomains","x-axios-cache-stale-if-error":"300000"}}}